{"name":"Todo-app-using-silex","tagline":"A simple todo application using Silex Framework.","body":"# ToDo-App-Using-Silex\r\n\r\nAim of this project is to learn Silex(A Symfony Micro framework).\r\n\r\nDemo Link: https://silextodoapp-satya5614.c9.io/web/todo\r\n\r\nRequirements:\r\n\r\n1. Composer to install Silex and other Symfony libraries\r\n2. MySql Database. Install the database structure using SQL.sql file located in config/SQL.sql\r\n","google":"","note":"Don't delete this file! It's used internally to help with page regeneration."}